 <Process label="MAJ_Retinopathie">
  <LocalVariables/>
  <PrimitiveTree size="1">
   <Control_Sequential>
    <Control_ChoiceIsEqual inChoices="$BDR" inValue="@BDR_D">
     <!--Mise a jour oeil droit-->
     <Control_Branch inProbability="0.07">
      <Data_SetVariable inValue_Type="String" inValue="BDR1" outVariable="@BDR_D"/>
      <Control_Nothing/>
     </Control_Branch>
     <Control_Sequential>
      <Control_Branch inProbability="0.12">
       <Data_SetVariable inValue_Type="String" inValue="BDR2" outVariable="@BDR_D"/>
       <Control_Nothing/>
      </Control_Branch>
      <Control_ChoiceIsEqual inChoices="$DMO" inValue="@DMO_D">
       <Control_Branch inProbability="0.03">
        <Data_SetVariable inValue_Type="String" inValue="DMO" outVariable="@DMO_D"/>
        <Control_Nothing/>
       </Control_Branch>
       <Control_Branch inProbability="0.3">
        <Data_SetVariable inValue_Type="String" inValue="CSMO" outVariable="@DMO_D"/>
        <Control_Nothing/>
       </Control_Branch>
       <Control_Branch inProbability="0.035">
		<Control_Sequential>
			<Data_SetVariable inValue_Type="String" inValue="Aveugle" outVariable="@DMO_D"/>
			<Data_SetVariable inValue_Type="String" inValue="Aveugle" outVariable="@BDR_D"/>
		</Control_Sequential>
        <Control_Nothing/>
       </Control_Branch>
       <Control_Nothing/>
       <Control_Nothing/>
      </Control_ChoiceIsEqual>
     </Control_Sequential>
     <Control_Sequential>
      <Control_Branch inProbability="0.045">
       <Data_SetVariable inValue_Type="String" inValue="PDR" outVariable="@BDR_D"/>
       <Control_Nothing/>
      </Control_Branch>
      <Control_ChoiceIsEqual inChoices="$DMO" inValue="@DMO_D">
       <Control_Branch inProbability="0.03">
        <Data_SetVariable inValue_Type="String" inValue="DMO" outVariable="@DMO_D"/>
        <Control_Nothing/>
       </Control_Branch>
       <Control_Branch inProbability="0.3">
        <Data_SetVariable inValue_Type="String" inValue="CSMO" outVariable="@DMO_D"/>
        <Control_Nothing/>
       </Control_Branch>
       <Control_Branch inProbability="0.035">
		<Control_Sequential>
			<Data_SetVariable inValue_Type="String" inValue="Aveugle" outVariable="@DMO_D"/>
			<Data_SetVariable inValue_Type="String" inValue="Aveugle" outVariable="@BDR_D"/>
		</Control_Sequential>
        <Control_Nothing/>
       </Control_Branch>
       <Control_Nothing/>
       <Control_Nothing/>
      </Control_ChoiceIsEqual>
     </Control_Sequential>
     <Control_Branch inProbability="0.035">
	  <Control_Sequential>
		<Data_SetVariable inValue_Type="String" inValue="Aveugle" outVariable="@BDR_D"/>
		<Data_SetVariable inValue_Type="String" inValue="Aveugle" outVariable="@DMO_D"/>
	  </Control_Sequential>
      <Control_ChoiceIsEqual inChoices="$DMO" inValue="@DMO_D">
       <Control_Branch inProbability="0.03">
        <Data_SetVariable inValue_Type="String" inValue="DMO" outVariable="@DMO_D"/>
        <Control_Nothing/>
       </Control_Branch>
       <Control_Branch inProbability="0.3">
        <Data_SetVariable inValue_Type="String" inValue="CSMO" outVariable="@DMO_D"/>
        <Control_Nothing/>
       </Control_Branch>
       <Control_Branch inProbability="0.035">
		<Control_Sequential>
			<Data_SetVariable inValue_Type="String" inValue="Aveugle" outVariable="@DMO_D"/>
			<Data_SetVariable inValue_Type="String" inValue="Aveugle" outVariable="@BDR_D"/>
		</Control_Sequential>
        <Control_Nothing/>
       </Control_Branch>
       <Control_Nothing/>
       <Control_Nothing/>
      </Control_ChoiceIsEqual>
     </Control_Branch>
     <Control_Nothing/>
     <Control_ChoiceIsEqual inChoices="$DMO" inValue="@DMO_D">
      <Control_Branch inProbability="0.03">
       <Data_SetVariable inValue_Type="String" inValue="DMO" outVariable="@DMO_D"/>
       <Control_Nothing/>
      </Control_Branch>
      <Control_Branch inProbability="0.3">
       <Data_SetVariable inValue_Type="String" inValue="CSMO" outVariable="@DMO_D"/>
       <Control_Nothing/>
      </Control_Branch>
      <Control_Branch inProbability="0.035">
	   <Control_Sequential>
		<Data_SetVariable inValue_Type="String" inValue="Aveugle" outVariable="@DMO_D"/>
		<Data_SetVariable inValue_Type="String" inValue="Aveugle" outVariable="@BDR_D"/>
	   </Control_Sequential>
       <Control_Nothing/>
      </Control_Branch>
      <Control_Nothing/>
      <Control_Nothing/>
     </Control_ChoiceIsEqual>
    </Control_ChoiceIsEqual>
    <Control_ChoiceIsEqual inChoices="$BDR" inValue="@BDR_G">
     <!--Mise a jour oeil gauche-->
     <Control_Branch inProbability="0.07">
      <Data_SetVariable inValue_Type="String" inValue="BDR1" outVariable="@BDR_G"/>
      <Control_Nothing/>
     </Control_Branch>
     <Control_Sequential>
      <Control_Branch inProbability="0.12">
       <Data_SetVariable inValue_Type="String" inValue="BDR2" outVariable="@BDR_G"/>
       <Control_Nothing/>
      </Control_Branch>
      <Control_ChoiceIsEqual inChoices="$DMO" inValue="@DMO_G">
       <Control_Branch inProbability="0.03">
        <Data_SetVariable inValue_Type="String" inValue="DMO" outVariable="@DMO_G"/>
        <Control_Nothing/>
       </Control_Branch>
       <Control_Branch inProbability="0.3">
        <Data_SetVariable inValue_Type="String" inValue="CSMO" outVariable="@DMO_G"/>
        <Control_Nothing/>
       </Control_Branch>
       <Control_Branch inProbability="0.035">
		<Control_Sequential>
			<Data_SetVariable inValue_Type="String" inValue="Aveugle" outVariable="@DMO_G"/>
			<Data_SetVariable inValue_Type="String" inValue="Aveugle" outVariable="@BDR_G"/>
		</Control_Sequential>
        <Control_Nothing/>
       </Control_Branch>
       <Control_Nothing/>
       <Control_Nothing/>
      </Control_ChoiceIsEqual>
     </Control_Sequential>
     <Control_Sequential>
      <Control_Branch inProbability="0.045">
       <Data_SetVariable inValue_Type="String" inValue="PDR" outVariable="@BDR_G"/>
       <Control_Nothing/>
      </Control_Branch>
      <Control_ChoiceIsEqual inChoices="$DMO" inValue="@DMO_G">
       <Control_Branch inProbability="0.03">
        <Data_SetVariable inValue_Type="String" inValue="DMO" outVariable="@DMO_G"/>
        <Control_Nothing/>
       </Control_Branch>
       <Control_Branch inProbability="0.3">
        <Data_SetVariable inValue_Type="String" inValue="CSMO" outVariable="@DMO_G"/>
        <Control_Nothing/>
       </Control_Branch>
       <Control_Branch inProbability="0.035">
		<Control_Sequential>
			<Data_SetVariable inValue_Type="String" inValue="Aveugle" outVariable="@DMO_G"/>
			<Data_SetVariable inValue_Type="String" inValue="Aveugle" outVariable="@BDR_G"/>
		</Control_Sequential>
        <Control_Nothing/>
       </Control_Branch>
       <Control_Nothing/>
       <Control_Nothing/>
      </Control_ChoiceIsEqual>
     </Control_Sequential>
     <Control_Branch inProbability="0.035">
	  <Control_Sequential>
		<Data_SetVariable inValue_Type="String" inValue="Aveugle" outVariable="@BDR_G"/>
		<Data_SetVariable inValue_Type="String" inValue="Aveugle" outVariable="@DMO_G"/>
	  </Control_Sequential>
      <Control_ChoiceIsEqual inChoices="$DMO" inValue="@DMO_G">
       <Control_Branch inProbability="0.03">
        <Data_SetVariable inValue_Type="String" inValue="DMO" outVariable="@DMO_G"/>
        <Control_Nothing/>
       </Control_Branch>
       <Control_Branch inProbability="0.3">
        <Data_SetVariable inValue_Type="String" inValue="CSMO" outVariable="@DMO_G"/>
        <Control_Nothing/>
       </Control_Branch>
       <Control_Branch inProbability="0.035">
		<Control_Sequential>
			<Data_SetVariable inValue_Type="String" inValue="Aveugle" outVariable="@DMO_G"/>
			<Data_SetVariable inValue_Type="String" inValue="Aveugle" outVariable="@BDR_G"/>
		</Control_Sequential>
        <Control_Nothing/>
       </Control_Branch>
       <Control_Nothing/>
       <Control_Nothing/>
      </Control_ChoiceIsEqual>
     </Control_Branch>
     <Control_Nothing/>
     <Control_ChoiceIsEqual inChoices="$DMO" inValue="@DMO_G">
      <Control_Branch inProbability="0.03">
       <Data_SetVariable inValue_Type="String" inValue="DMO" outVariable="@DMO_G"/>
       <Control_Nothing/>
      </Control_Branch>
      <Control_Branch inProbability="0.3">
       <Data_SetVariable inValue_Type="String" inValue="CSMO" outVariable="@DMO_G"/>
       <Control_Nothing/>
      </Control_Branch>
      <Control_Branch inProbability="0.035">
		<Control_Sequential>
			<Data_SetVariable inValue_Type="String" inValue="Aveugle" outVariable="@DMO_G"/>
			<Data_SetVariable inValue_Type="String" inValue="Aveugle" outVariable="@BDR_G"/>
		</Control_Sequential>
       <Control_Nothing/>
      </Control_Branch>
      <Control_Nothing/>
      <Control_Nothing/>
     </Control_ChoiceIsEqual>
    </Control_ChoiceIsEqual>
   </Control_Sequential>
  </PrimitiveTree>
 </Process>
